pymtattl/__init__.py
pymtattl/core.py
pymtattl/sqlalchemy_declarative.py
pymtattl/utils.py
pymtattl-1.1.0.dist-info/LICENSE
pymtattl-1.1.0.dist-info/METADATA
pymtattl-1.1.0.dist-info/WHEEL
pymtattl-1.1.0.dist-info/top_level.txt
pymtattl-1.1.0.dist-info/RECORD
