Metadata-Version: 2.1
Name: pymtattl
Version: 1.1.0
Summary: Download and store MTA turnstile data
Home-page: https://github.com/Ritaotao/pymtattl
Author: Ritaotao
Author-email: ritaotao28@gmail.com
License: MIT
Keywords: mta,turnstile,data,traffic
Platform: UNKNOWN
Classifier: Programming Language :: Python :: 3
Classifier: Topic :: Database
Classifier: Topic :: Utilities
Classifier: Topic :: Education
Requires-Dist: beautifulsoup4
Requires-Dist: pandas
Requires-Dist: sqlalchemy
